py_event_sourcing/__init__.py
py_event_sourcing/models.py
py_event_sourcing/protocols.py
py_event_sourcing/stream.py
py_event_sourcing/adaptors/__init__.py
py_event_sourcing/adaptors/sqlite/__init__.py
py_event_sourcing/adaptors/sqlite/factory.py
py_event_sourcing/adaptors/sqlite/filter_parser.py
py_event_sourcing/adaptors/sqlite/handle.py
py_event_sourcing/adaptors/sqlite/notifier.py
py_event_sourcing/adaptors/sqlite/resource_manager.py
py_event_sourcing-1.0.3.dist-info/METADATA
py_event_sourcing-1.0.3.dist-info/WHEEL
py_event_sourcing-1.0.3.dist-info/licenses/LICENSE
py_event_sourcing-1.0.3.dist-info/RECORD
