Metadata-Version: 2.4
Name: py-event-sourcing
Version: 1.0.3
Summary: A minimal, `asyncio`-native event sourcing library
Project-URL: Homepage, https://github.com/johnlogsdon/py-event-sourcing
Project-URL: Documentation, https://github.com/johnlogsdon/py-event-sourcing#readme
Project-URL: Repository, https://github.com/johnlogsdon/py-event-sourcing.git
Project-URL: Issues, https://github.com/johnlogsdon/py-event-sourcing/issues
Project-URL: Changelog, https://github.com/johnlogsdon/py-event-sourcing/blob/main/CHANGELOG.md
Author-email: John <john@example.com>
Maintainer-email: John <john@example.com>
License: MIT
License-File: LICENSE
Keywords: asyncio,database,event-sourcing,sqlite,stream-processing
Classifier: Development Status :: 4 - Beta
Classifier: Framework :: AsyncIO
Classifier: Intended Audience :: Developers
Classifier: License :: OSI Approved :: MIT License
Classifier: Operating System :: OS Independent
Classifier: Programming Language :: Python :: 3
Classifier: Programming Language :: Python :: 3.11
Classifier: Programming Language :: Python :: 3.12
Classifier: Programming Language :: Python :: 3.13
Classifier: Topic :: Database
Classifier: Topic :: Software Development :: Libraries :: Python Modules
Requires-Python: >=3.11
Requires-Dist: aiosqlite>=0.19.0
Requires-Dist: pydantic>=2.11.7
